[
  {
    "category_id": 0,
    "product_id": 0,
    "product_name": "برگر گوشت و قارچ",
    "description": "این برگر از گوشت گاو تازه و قارچ‌های تازه و خوشمزه تهیه شده است. هر برگر از این محصول حاوی حدود ۳۷۰ کیلوکالری است.",
    "product_image": "assets/images/sandwich1'",
    "price": "180000.00",
    "time_of_preparation": 15,
    "slug": "'meat_mushroom'",
    "average_rating": "0.0"
  },
  {
    "category_id": 0,
    "product_id": 1,
    "product_name": "برگر گوشت و پنیر",
    "description": "این برگر از گوشت گاو تازه و قارچ‌های تازه و خوشمزه تهیه شده است. هر برگر از این محصول حاوی حدود ۳۷۰ کیلوکالری است.",
    "product_image": "assets/images/sandwich2'",
    "price": "180000.00",
    "time_of_preparation": 15,
    "slug": "'meat_cheese'",
    "average_rating": "0.0"
  },
  {
    "category_id": 0,
    "product_id": 2,
    "product_name": "برگر استیک",
    "description": "این برگر با استفاده از گوشت گاو تازه و آماده‌سازی به روش استیک تهیه شده است",
    "product_image": "assets/images/sandwich3'",
    "price": "180000.00",
    "time_of_preparation": 15,
    "slug": "'stake_burger'",
    "average_rating": "0.0"
  },
  {
    "category_id": 0,
    "product_id": 3,
    "product_name": "برگر دودی",
    "description": "این برگر با استفاده از گوشت گاو تازه و دودی شده تهیه شده است، برای بخشی از طعم معدنی خود. هر برگر از این محصول حاوی حدود ۳۸۰ کیلوکالری است.",
    "product_image": "assets/images/sandwich4'",
    "price": "180000.00",
    "time_of_preparation": 20,
    "slug": "'smokey_burger",
    "average_rating": "0.0"
  },
  {
    "category_id": 0,
    "product_id": 4,
    "product_name": "برگر دوبل",
    "description": "این برگر دوبل از دو لایه گوشت گاو تازه تهیه شده است، با لایه‌های پنیر و سس مخصوص درون آن. هر برگر از این محصول حاوی حدود ۴۵۰ کیلوکالری است.",
    "product_image": "assets/images/sandwich5'",
    "price": "180000.00",
    "time_of_preparation": 15,
    "slug": "'double_burger'",
    "average_rating": "0.0"
  },
  {
    "category_id": 0,
    "product_id": 5,
    "product_name": "برگر مخصوص",
    "description": "این برگر مخصوص از گوشت گاو تازه و آماده‌سازی با ترکیبات منحصر به فرد و رسیدن به طعمی خاص تهیه شده است. هر برگر از این محصول حاوی حدود ۴۵۰ کیلوکالری است.",
    "product_image": "assets/images/sandwich6'",
    "price": "199000.00",
    "time_of_preparation": 25,
    "slug": "'special_burger'",
    "average_rating": "0.0"
  },
  {
    "category_id": 1,
    "product_id": 6,
    "product_name": "نوشابه مشکی لیوانی",
    "description": "این نوشابه معروف از مخلوطی از مواد طبیعی و افزودنی‌های مصنوعی تهیه شده است. هر لیوان از این نوشابه حاوی حدود ۱۵۰ کیلوکالری است",
    "product_image": "assets/images/soda1'",
    "price": "19000.00",
    "time_of_preparation": 2,
    "slug": "'soda_cup'",
    "average_rating": "0.0"
  },
  {
    "category_id": 1,
    "product_id": 7,
    "product_name": "نوشابه مشکی قوطی",
    "description": "این نوشابه معروف از مخلوطی از مواد طبیعی و افزودنی‌های مصنوعی تهیه شده است. هر لیوان از این نوشابه حاوی حدود ۱۵۰ کیلوکالری است",
    "product_image": "assets/images/soda2'",
    "price": "29000.00",
    "time_of_preparation": 2,
    "slug": "'soda_can'",
    "average_rating": "0.0"
  },
  {
    "category_id": 1,
    "product_id": 8,
    "product_name": "نوشابه زیرو",
    "description": "این نوشابه معروف از مخلوطی از مواد طبیعی و افزودنی‌های مصنوعی تهیه شده است. هر لیوان از این نوشابه حاوی حدود ۱۵۰ کیلوکالری است",
    "product_image": "assets/images/soda3'",
    "price": "49000.00",
    "time_of_preparation": 2,
    "slug": "'zero_soda'",
    "average_rating": "0.0"
  },
  {
    "category_id": 1,
    "product_id": 9,
    "product_name": "نوشابه کوکاکولا شیشه ای",
    "description": "این نوشابه معروف از مخلوطی از مواد طبیعی و افزودنی‌های مصنوعی تهیه شده است. هر لیوان از این نوشابه حاوی حدود ۱۵۰ کیلوکالری است",
    "product_image": "assets/images/soda4'",
    "price": "34000.00",
    "time_of_preparation": 2,
    "slug": "'bottle_soda",
    "average_rating": "0.0"
  },
  {
    "category_id": 1,
    "product_id": 10,
    "product_name": "نوشابه کوکاکولا",
    "description": "این نوشابه معروف از مخلوطی از مواد طبیعی و افزودنی‌های مصنوعی تهیه شده است. هر لیوان از این نوشابه حاوی حدود ۱۵۰ کیلوکالری است",
    "product_image": "assets/images/soda5'",
    "price": "34000.00",
    "time_of_preparation": 2,
    "slug": "'family_soda'",
    "average_rating": "0.0"
  },
  {
    "category_id": 2,
    "product_id": 11,
    "product_name": "پیتزا گوشت و قارچ",
    "description": "پیتزا گوشت و قارچ توضیحات: این پیتزا با استفاده از خمیر تازه و رویه‌ای شامل گوشت و قارچ تهیه شده است. هر برش از این پیتزا حاوی حدود ۳۵۰ کیلوکالری است.",
    "product_image": "assets/images/pizza1'",
    "price": "199000.00",
    "time_of_preparation": 25,
    "slug": "'pizza_meat_mushroom'",
    "average_rating": "0.0"
  },
  {
    "category_id": 2,
    "product_id": 12,
    "product_name": "پیتزا ژامبون",
    "description": "پیتزا ژامبون توضیحات: این پیتزا با استفاده از خمیر تازه و رویه‌ای شامل ژامبون و مواد افزودنی دیگر تهیه شده است. هر برش از این پیتزا حاوی حدود ۳۲۰ کیلوکالری است.",
    "product_image": "assets/images/pizza2'",
    "price": "249000.00",
    "time_of_preparation": 25,
    "slug": "'pizza_zhambon'",
    "average_rating": "0.0"
  },
  {
    "category_id": 2,
    "product_id": 13,
    "product_name": "پیتزا رست بیف",
    "description": "این پیتزا با استفاده از خمیر تازه و رویه‌ای شامل گوشت بیف و مواد افزودنی دیگر تهیه شده است. هر برش از این پیتزا حاوی حدود ۳۵۰ کیلوکالری است.",
    "product_image": "assets/images/pizza3'",
    "price": "259000.00",
    "time_of_preparation": 25,
    "slug": "'pizza_roast_beef'",
    "average_rating": "0.0"
  },
  {
    "category_id": 2,
    "product_id": 14,
    "product_name": "پیتزا مخلوط",
    "description": "این پیتزا شامل ترکیبی از مواد مختلف از جمله گوشت، قارچ، فلفل دلمه، زیتون",
    "product_image": "assets/images/pizza4'",
    "price": "199000.00",
    "time_of_preparation": 25,
    "slug": "'pizza_blended'",
    "average_rating": "0.0"
  },
  {
    "category_id": 2,
    "product_id": 15,
    "product_name": "پیتزا گوشت",
    "description": "این پیتزا با استفاده از خمیر تازه و رویه‌ای شامل گوشت و مواد افزودنی دیگر تهیه شده است. هر برش از این پیتزا حاوی حدود ۳۰۰ کیلوکالری است.",
    "product_image": "assets/images/pizza5'",
    "price": "259000.00",
    "time_of_preparation": 25,
    "slug": "'pizza_meat'",
    "average_rating": "0.0"
  },
  {
    "category_id": 2,
    "product_id": 16,
    "product_name": "پیتزا گوشت سافاری",
    "description": "این پیتزا شامل ترکیبی از گوشت گاو و مواد افزودنی دیگر است، با طعم و احساسی ماجراجویانه. هر برش از این پیتزا حاوی حدود ۳۵۰ کیلوکالری است.",
    "product_image": "assets/images/pizza6'",
    "price": "239000.00",
    "time_of_preparation": 45,
    "slug": "'pizza_safari'",
    "average_rating": "0.0"
  }
]
